p2pfl/__init__.py
p2pfl/__main__.py
p2pfl/exceptions.py
p2pfl/experiment.py
p2pfl/node.py
p2pfl/node_state.py
p2pfl/settings.py
p2pfl/certificates/client_ext.cnf
p2pfl/certificates/gen-certs.sh
p2pfl/certificates/openssl.cnf
p2pfl/certificates/server_ext.cnf
p2pfl/communication/__init__.py
p2pfl/communication/commands/__init__.py
p2pfl/communication/commands/command.py
p2pfl/communication/commands/message/__init__.py
p2pfl/communication/commands/message/heartbeat_command.py
p2pfl/communication/commands/message/metrics_command.py
p2pfl/communication/commands/message/model_initialized_command.py
p2pfl/communication/commands/message/models_agregated_command.py
p2pfl/communication/commands/message/models_ready_command.py
p2pfl/communication/commands/message/pre_send_model_command.py
p2pfl/communication/commands/message/start_learning_command.py
p2pfl/communication/commands/message/stop_learning_command.py
p2pfl/communication/commands/message/vote_train_set_command.py
p2pfl/communication/commands/weights/__init__.py
p2pfl/communication/commands/weights/full_model_command.py
p2pfl/communication/commands/weights/init_model_command.py
p2pfl/communication/commands/weights/partial_model_command.py
p2pfl/communication/protocols/__init__.py
p2pfl/communication/protocols/communication_protocol.py
p2pfl/communication/protocols/exceptions.py
p2pfl/communication/protocols/protobuff/__init__.py
p2pfl/communication/protocols/protobuff/client.py
p2pfl/communication/protocols/protobuff/gossiper.py
p2pfl/communication/protocols/protobuff/heartbeater.py
p2pfl/communication/protocols/protobuff/neighbors.py
p2pfl/communication/protocols/protobuff/protobuff_communication_protocol.py
p2pfl/communication/protocols/protobuff/server.py
p2pfl/communication/protocols/protobuff/grpc/__init__.py
p2pfl/communication/protocols/protobuff/grpc/address.py
p2pfl/communication/protocols/protobuff/grpc/client.py
p2pfl/communication/protocols/protobuff/grpc/server.py
p2pfl-0.4.4.dist-info/METADATA
p2pfl-0.4.4.dist-info/WHEEL
p2pfl-0.4.4.dist-info/entry_points.txt
p2pfl-0.4.4.dist-info/licenses/LICENSE.md
p2pfl-0.4.4.dist-info/RECORD
