Metadata-Version: 2.4
Name: p2pfl
Version: 0.4.4
Summary: A p2p federated learning framework
Project-URL: Homepage, https://p2pfl.com
Project-URL: Repository, https://github.com/p2pfl/p2pfl
Project-URL: Documentation, https://p2pfl.github.io/p2pfl/
Author-email: Pedro Guijas <pguijas@gmail.com>
License-Expression: GPL-3.0-only
License-File: LICENSE.md
Keywords: data privacy,data security,decentralized,federated learning,fl,p2p,peer to peer,pytorch
Requires-Python: <3.13,>=3.10.0
Requires-Dist: click==8.1.8
Requires-Dist: datasets==2.15.0
Requires-Dist: grpcio-tools<2,>=1.62.0
Requires-Dist: grpcio<2,>=1.62.0
Requires-Dist: matplotlib<4,>=3.8.3
Requires-Dist: numpy<2.0,>=1.20
Requires-Dist: pandas<3,>=2.2.3
Requires-Dist: protobuf>=5.29.1
Requires-Dist: psutil<6,>=5.9.8
Requires-Dist: pyyaml<7,>=6.0.2
Requires-Dist: ray<3,>=2.43.0
Requires-Dist: tqdm<5,>=4.67.0
Requires-Dist: typer<0.13,>=0.12.3
Provides-Extra: dp
Requires-Dist: opendp>=0.13.0; extra == 'dp'
Provides-Extra: flax
Requires-Dist: flax<0.11,>=0.10.0; extra == 'flax'
Provides-Extra: tensorflow
Requires-Dist: keras<4,>=3.5.0; extra == 'tensorflow'
Requires-Dist: tensorflow<3,>=2.18.0; extra == 'tensorflow'
Requires-Dist: types-tensorflow<3,>=2.17.0.20240820; extra == 'tensorflow'
Provides-Extra: torch
Requires-Dist: lightning<3,>=2.4.0; extra == 'torch'
Requires-Dist: torch<3,>=2.2.1; extra == 'torch'
Requires-Dist: torchmetrics<2,>=1.3.1; extra == 'torch'
Requires-Dist: torchvision<0.18,>=0.17.1; extra == 'torch'
Provides-Extra: wandb
Requires-Dist: wandb<0.21,>=0.20.1; extra == 'wandb'
